pybic/__init__.py
pybic/bic.py
pybic/cmd.py
pybic/listener.py
pybic/utils.py
pybic-0.3.0.dist-info/LICENSE
pybic-0.3.0.dist-info/METADATA
pybic-0.3.0.dist-info/WHEEL
pybic-0.3.0.dist-info/RECORD
